loglib/__init__.py
loglib/main_enabler.py
loglib/base/__init__.py
loglib/base/emitter.py
loglib/base/handler.py
loglib/base/thread.py
loglib/fluentbit/__init__.py
loglib/fluentbit/enabler.py
loglib/loki/__init__.py
loglib/loki/emitter.py
loglib/loki/enabler.py
loglib/loki/fetcher.py
loglib/loki/handler.py
loglib/opensearch/__init__.py
loglib/opensearch/fetcher.py
my_loglib-0.1.3.dist-info/LICENSE
my_loglib-0.1.3.dist-info/METADATA
my_loglib-0.1.3.dist-info/WHEEL
my_loglib-0.1.3.dist-info/top_level.txt
my_loglib-0.1.3.dist-info/RECORD
