Metadata-Version: 2.1
Name: my-loglib
Version: 0.1.3
Summary: A Library for log management
Home-page: UNKNOWN
Author: UsmonbekRavshanov
Author-email: usmonbekravshanov@gmail.com
License: Apache License, Version 2.0
Platform: UNKNOWN
Requires-Dist: fluent-logger (==0.10.0)
Requires-Dist: requests (>=2.28.1)
Requires-Dist: urllib3 (==1.26.15)
